MANIFEST.in
README.md
setup.cfg
setup.py
traits_finder/Traits_MG.py
traits_finder/Traits_WG.py
traits_finder/__init__.py
traits_finder/__main__.py
traits_finder.egg-info/PKG-INFO
traits_finder.egg-info/SOURCES.txt
traits_finder.egg-info/dependency_links.txt
traits_finder.egg-info/entry_points.txt
traits_finder.egg-info/requires.txt
traits_finder.egg-info/top_level.txt
traits_finder/database/.DS_Store
traits_finder/database/85_otus.fasta
traits_finder/database/85_otus.fasta.all.V4_V5.fasta
traits_finder/database/Butyrate.pro.fasta
traits_finder/database/Butyrate.pro.fasta.mapping.txt
traits_finder/database/SARG.db.fasta
traits_finder/database/SARG.db.fasta.mapping.txt
traits_finder/database/all_KO30.pro.fasta
traits_finder/database/all_KO30.pro.fasta.length
traits_finder/database/all_KO30_name.list
traits_finder/scripts/.DS_Store
traits_finder/scripts/Cell_completeness_WG.py
traits_finder/scripts/Cell_number_MG.py
traits_finder/scripts/Extract.16S.MG.py
traits_finder/scripts/Extract.16S.WG.py
traits_finder/scripts/Extract.MG.py
traits_finder/scripts/Extract.WG.py
traits_finder/scripts/Filter.MG.py
traits_finder/scripts/Filter.WG.py
traits_finder/scripts/Format.MG.py
traits_finder/scripts/Format.WG.py
traits_finder/scripts/HGT_finder_sum.py
traits_finder/scripts/Merge.dataset.py
traits_finder/scripts/Search.MG.py
traits_finder/scripts/Search.WG.py
traits_finder/scripts/Traits_summary_MG.py
traits_finder/scripts/Traits_summary_WG.py
traits_finder/scripts/VCF.reader.py
traits_finder/scripts/remove.duplicated.seq.py
traits_finder/scripts/undone.MG.py
traits_finder/scripts/undone.WG.py