Metadata-Version: 2.1
Name: traits-finder
Version: 1.6
Summary: search and summarize traits in genomes and metagenomes
Home-page: https://github.com/caozhichongchong/traits_finder
Author: Anni Zhang
Author-email: anniz44@mit.edu
License: MIT
Keywords: metagenomes,genomes,function,traits
Platform: UNKNOWN
Classifier: Programming Language :: Python :: 3
